pylibvirt/__init__.py
pylibvirt/__main__.py
pylibvirt/modules/__init__.py
pylibvirt/modules/devices/__init__.py
pylibvirt/modules/devices/controller.py
pylibvirt/modules/devices/cpu.py
pylibvirt/modules/devices/device.py
pylibvirt/modules/devices/file_system.py
pylibvirt/modules/devices/graphic.py
pylibvirt/modules/devices/interface.py
pylibvirt/modules/devices/rng.py
pylibvirt/modules/devices/sound.py
pylibvirt/modules/devices/strorage.py
pylibvirt/modules/devices/usb.py
pylibvirt/modules/devices/video.py
pylibvirt/modules/devices/xml.py
pylibvirt/modules/domain.py
pylibvirt/modules/network.py
pylibvirt/modules/storage.py
pylibvirt/modules/volume.py
pylibvirt/template/template.yml
pylibvirt/template/test.json
pylibvirt-0.0.12.dist-info/LICENSE
pylibvirt-0.0.12.dist-info/METADATA
pylibvirt-0.0.12.dist-info/WHEEL
pylibvirt-0.0.12.dist-info/entry_points.txt
pylibvirt-0.0.12.dist-info/RECORD
