Metadata-Version: 2.1
Name: pylibvirt
Version: 0.0.12
Summary: Python package to orchestrate libvirt API from yaml declaration file
Home-page: https://gitlab.com/Sevolith/Python-Libvirt/
License: GPL-2.0-or-later
Author: Sevolith
Author-email: contactsevolith@gmail.com
Requires-Python: >=3.9,<4.0
Classifier: License :: OSI Approved :: GNU General Public License v2 or later (GPLv2+)
Classifier: Programming Language :: Python :: 3
Classifier: Programming Language :: Python :: 3.9
Classifier: Programming Language :: Python :: 3.10
Classifier: Programming Language :: Python :: 3.11
Classifier: Programming Language :: Python :: 3.12
Requires-Dist: PyYAML (<7.0.0)
Requires-Dist: cffi (>=1.16.0)
Requires-Dist: click (>=8.0.1,<9.0.0)
Requires-Dist: defusedxml (>=0.7.1,<0.8.0)
Requires-Dist: libvirt-python (<13.0.0)
Requires-Dist: rich (>=10.6.0,<11.0.0)
Project-URL: Repository, https://gitlab.com/Sevolith/Python-Libvirt/
